tenc/__init__.py
tenc/cli.py
tenc/core.py
tenc-1.2.dist-info/LICENSE
tenc-1.2.dist-info/METADATA
tenc-1.2.dist-info/WHEEL
tenc-1.2.dist-info/entry_points.txt
tenc-1.2.dist-info/top_level.txt
tenc-1.2.dist-info/RECORD
