Metadata-Version: 2.1
Name: tenc
Version: 1.2
Summary: A small package to de- and encrypt strings
Home-page: UNKNOWN
Author: Philip Stapelfeldt
Author-email: p.stapelfeldt@nanogiants.de
License: UNKNOWN
Platform: UNKNOWN
Requires-Python: >=2.7
Requires-Dist: PyCryptodome
